vdsolver/__init__.py
vdsolver/core/__init__.py
vdsolver/core/base.py
vdsolver/core/boundaries.py
vdsolver/core/plot.py
vdsolver/core/probs.py
vdsolver/core/targets.py
vdsolver/sims/__init__.py
vdsolver/sims/essimulator.py
vdsolver/templates/backtrace-solver-hybrid.py.tmp
vdsolver/templates/backtrace-solver.py.tmp
vdsolver/templates/vdist-solver-current.py.tmp
vdsolver/templates/vdist-solver-density.py.tmp
vdsolver/templates/vdist-solver1d-hybrid.py.tmp
vdsolver/templates/vdist-solver1d.py.tmp
vdsolver/templates/vdist-solver2d-hybrid.py.tmp
vdsolver/templates/vdist-solver2d.py.tmp
vdsolver/tools/__init__.py
vdsolver/tools/gentemp.py
vdsolver/tools/emses/__init__.py
vdsolver/tools/emses/utils.py
vdsolver/tools/hybrid/__init__.py
vdsolver/tools/hybrid/data.py
vdsolver/tools/hybrid/sim.py
vdist_solver-1.1.3.dist-info/LICENSE
vdist_solver-1.1.3.dist-info/METADATA
vdist_solver-1.1.3.dist-info/WHEEL
vdist_solver-1.1.3.dist-info/entry_points.txt
vdist_solver-1.1.3.dist-info/top_level.txt
vdist_solver-1.1.3.dist-info/RECORD
