Metadata-Version: 2.1
Name: vdist-solver
Version: 1.1.3
Summary: Velocity distribution function solver using Liouville's theorem
Home-page: https://github.com/Nkzono99/vdist-solver
Author: Nkzono99
Author-email: 210x218x@gsuite.stu.kobe-u.ac.jp
Classifier: Programming Language :: Python :: 3
Classifier: License :: OSI Approved :: MIT License
Classifier: Operating System :: OS Independent
Requires-Python: >=3.7
License-File: LICENSE
Requires-Dist: numpy
Requires-Dist: matplotlib
Requires-Dist: emout
Requires-Dist: tqdm
Requires-Dist: scipy
Requires-Dist: Deprecated
